mia_vgg/__init__.py
mia_vgg/aia.py
mia_vgg/aia_dataset.py
mia_vgg/cross_val_idx.py
mia_vgg/generate.py
mia_vgg/generate_antoine.py
mia_vgg/generate_labels.py
mia_vgg/mia.py
mia_vgg/synthetic_dataset.py
mia_vgg/train_generator.py
mia_vgg/train_generator_antoine.py
mia_vgg/train_generator_experimental.py
mia_vgg/train_target.py
mia_vgg/train_target_over.py
mia_vgg/plot/__init__.py
mia_vgg/plot/aia.py
mia_vgg/plot/gan_loss.py
mia_vgg/plot/mia.py
mia_vgg/plot/target_loss.py
mia_vgg/plot/utility.py
mia_vgg-0.0.171.dist-info/METADATA
mia_vgg-0.0.171.dist-info/WHEEL
mia_vgg-0.0.171.dist-info/top_level.txt
mia_vgg-0.0.171.dist-info/RECORD
