Metadata-Version: 2.1
Name: mia_vgg
Version: 0.0.171
Summary: MIA on VGG dataset using pytorch
Author-email: Jan Aalmoes <jan.aalmoes@protonmail.com>
Project-URL: Homepage, https://github.com/pypa/sampleproject
Project-URL: Issues, https://github.com/pypa/sampleproject/issues
Classifier: Programming Language :: Python :: 3
Classifier: License :: OSI Approved :: MIT License
Classifier: Operating System :: OS Independent
Requires-Python: >=3.8
Requires-Dist: torchvision
Requires-Dist: gdown
Requires-Dist: matplotlib
Requires-Dist: scikit-learn
